sec_share/__init__.py
sec_share/cli.py
sec_share-0.1.4.dist-info/LICENSE
sec_share-0.1.4.dist-info/METADATA
sec_share-0.1.4.dist-info/WHEEL
sec_share-0.1.4.dist-info/entry_points.txt
sec_share-0.1.4.dist-info/top_level.txt
sec_share-0.1.4.dist-info/RECORD
